flowetl/__init__.py
flowetl/_version.py
flowetl/cli.py
flowetl/util.py
flowetl/mixins/__init__.py
flowetl/mixins/fixed_sql_mixin.py
flowetl/mixins/fixed_sql_with_params_mixin.py
flowetl/mixins/table_name_macros_mixin.py
flowetl/mixins/wrapping_sql_mixin.py
flowetl/operators/__init__.py
flowetl/operators/add_constraints_operator.py
flowetl/operators/analyze_operator.py
flowetl/operators/attach_operator.py
flowetl/operators/cluster_operator.py
flowetl/operators/create_foreign_staging_table_operator.py
flowetl/operators/create_indexes_operator.py
flowetl/operators/create_staging_view_operator.py
flowetl/operators/extract_from_foreign_table_operator.py
flowetl/operators/extract_from_view_operator.py
flowetl/operators/qa_check_operator.py
flowetl/operators/update_etl_table_operator.py
flowetl/operators/update_location_ids_table_operator.py
flowetl/qa_checks/qa_checks/count_added_rows.sql
flowetl/qa_checks/qa_checks/count_duplicated.sql
flowetl/qa_checks/qa_checks/count_duplicates.sql
flowetl/qa_checks/qa_checks/count_imeis.sql
flowetl/qa_checks/qa_checks/count_imsis.sql
flowetl/qa_checks/qa_checks/count_locatable_events.sql
flowetl/qa_checks/qa_checks/count_locatable_location_ids.sql
flowetl/qa_checks/qa_checks/count_location_ids.sql
flowetl/qa_checks/qa_checks/count_msisdns.sql
flowetl/qa_checks/qa_checks/count_null_imeis.sql
flowetl/qa_checks/qa_checks/count_null_imsis.sql
flowetl/qa_checks/qa_checks/count_null_location_ids.sql
flowetl/qa_checks/qa_checks/earliest_timestamp.sql
flowetl/qa_checks/qa_checks/latest_timestamp.sql
flowetl/qa_checks/qa_checks/max_msisdns_per_imei.sql
flowetl/qa_checks/qa_checks/max_msisdns_per_imsi.sql
flowetl/qa_checks/qa_checks/calls/count_added_rows_outgoing.sql
flowetl/qa_checks/qa_checks/calls/count_null_counterparts.sql
flowetl/qa_checks/qa_checks/calls/count_null_durations.sql
flowetl/qa_checks/qa_checks/calls/count_onnet_msisdns.sql
flowetl/qa_checks/qa_checks/calls/count_onnet_msisdns_incoming.sql
flowetl-1.34.0.dist-info/METADATA
flowetl-1.34.0.dist-info/WHEEL
flowetl-1.34.0.dist-info/entry_points.txt
flowetl-1.34.0.dist-info/top_level.txt
flowetl-1.34.0.dist-info/RECORD
